<?xml version="1.0" encoding="UTF-8"?>
<!DOCTYPE hibernate-reverse-engineering PUBLIC "-//Hibernate/Hibernate Reverse Engineering DTD 3.0//EN" "http://hibernate.sourceforge.net/hibernate-reverse-engineering-3.0.dtd">
<hibernate-reverse-engineering>
  <schema-selection match-catalog="gerprodb"/>
  <table-filter match-name="correcao"/>
  <table-filter match-name="cronograma"/>
  <table-filter match-name="equipe"/>
  <table-filter match-name="item"/>
  <table-filter match-name="lista_funcao"/>
  <table-filter match-name="pergunta"/>
  <table-filter match-name="periodo"/>
  <table-filter match-name="proposta"/>
  <table-filter match-name="proposta_item"/>
  <table-filter match-name="resposta"/>
  <table-filter match-name="status"/>
  <table-filter match-name="tipo_usuario"/>
  <table-filter match-name="usuario"/>
</hibernate-reverse-engineering>
